Metadata-Version: 2.1
Name: crcmodbus
Version: 1.2
Summary: crc16
Home-page: https://gitee.com/jdhxyy/crc16-python
Author: jdh99
Author-email: jdh821@163.com
License: UNKNOWN
Platform: UNKNOWN
